LICENSE
MANIFEST.in
README.md
pyproject.toml
requirements-test.txt
requirements.txt
setup.cfg
setup.py
deployment/__init__.py
deployment/bff/__init__.py
deployment/bff/app/__init__.py
deployment/bff/app/app.py
deployment/bff/app/decorators.py
deployment/bff/app/settings.py
deployment/bff/app/v1/__init__.py
deployment/bff/app/v1/models/__init__.py
deployment/bff/app/v1/models/admin.py
deployment/bff/app/v1/models/search.py
deployment/bff/app/v1/models/shared.py
deployment/bff/app/v1/routers/__init__.py
deployment/bff/app/v1/routers/admin.py
deployment/bff/app/v1/routers/helper.py
deployment/bff/app/v1/routers/search.py
jina_now.egg-info/PKG-INFO
jina_now.egg-info/SOURCES.txt
jina_now.egg-info/dependency_links.txt
jina_now.egg-info/entry_points.txt
jina_now.egg-info/not-zip-safe
jina_now.egg-info/requires.txt
jina_now.egg-info/top_level.txt
now/README.md
now/__init__.py
now/constants.py
now/custom-spinners.json
now/demo_data.py
now/dialog.py
now/kind.yml
now/now_dataclasses.py
now/run_all_k8s.py
now/run_backend.py
now/utils.py
now/admin/__init__.py
now/admin/benchmark_flow.py
now/admin/build_datasets.py
now/admin/deploy_text_to_video.py
now/admin/flow_results.py
now/admin/run_performance_test.py
now/admin/search.py
now/admin/update_api_keys.py
now/admin/update_email.py
now/admin/utils.py
now/app/__init__.py
now/app/base/__init__.py
now/app/base/app.py
now/app/base/flow.yml
now/app/base/preprocess.py
now/app/search_app/__init__.py
now/app/search_app/app.py
now/app/search_app/indexer_utils.py
now/cli/__init__.py
now/cli/parser.py
now/client/__init__.py
now/common/__init__.py
now/common/detect_schema.py
now/common/options.py
now/common/testing.py
now/common/flow/flow-external-clip.yml
now/data_loading/__init__.py
now/data_loading/convert_datasets_to_jpeg.py
now/data_loading/create_dataclass.py
now/data_loading/data_loading.py
now/data_loading/elasticsearch/__init__.py
now/data_loading/elasticsearch/connector.py
now/data_loading/elasticsearch/data_extractor.py
now/deployment/__init__.py
now/deployment/deployment.py
now/deployment/elastic_kind.yml
now/deployment/flow.py
now/deployment/k8s_backend-svc-lb.yml
now/deployment/k8s_backend-svc-node.yml
now/deployment/k8s_playground-deployment.yml
