Metadata-Version: 2.1
Name: jina-now
Version: 0.0.50
Summary: Jina NOW - get your neural search case up and running in minutes.
Home-page: https://github.com/jina-ai/now/
Author: Jina AI
Author-email: hello@jina.ai
License: Apache 2.0
Download-URL: https://github.com/jina-ai/now/tags
Project-URL: Documentation, https://docs.jina.ai
Project-URL: Source, https://github.com/jina-ai/now
Project-URL: Tracker, https://github.com/jina-ai/now/issues
Keywords: jina neural-search neural-network deep-learning now private data democratization
Platform: UNKNOWN
Classifier: Development Status :: 5 - Production/Stable
Classifier: Intended Audience :: Developers
Classifier: Intended Audience :: Education
Classifier: Intended Audience :: Science/Research
Classifier: Programming Language :: Python :: 3.7
Classifier: Programming Language :: Python :: 3.8
Classifier: Programming Language :: Python :: 3.9
Classifier: Programming Language :: Python :: 3.10
Classifier: Environment :: Console
Classifier: License :: OSI Approved :: Apache Software License
Classifier: Operating System :: OS Independent
Classifier: Topic :: Scientific/Engineering :: Artificial Intelligence
Provides-Extra: test
